pyportus-0.6.1.dist-info/METADATA
pyportus-0.6.1.dist-info/WHEEL
pyportus/__init__.py
pyportus/checker.py
pyportus/util.py
pyportus/__pycache__/checker.cpython-36.pyc
pyportus/__pycache__/util.cpython-36.pyc
pyportus/__pycache__/__init__.cpython-36.pyc
pyportus/pyportus.cpython-36m-x86_64-linux-gnu.so
pyportus-0.6.1.dist-info/RECORD
